qmkpy/__init__.py
qmkpy/algorithms.py
qmkpy/checks.py
qmkpy/io.py
qmkpy/qmkp.py
qmkpy/util.py
qmkpy-1.2.0.dist-info/LICENSE
qmkpy-1.2.0.dist-info/METADATA
qmkpy-1.2.0.dist-info/WHEEL
qmkpy-1.2.0.dist-info/top_level.txt
qmkpy-1.2.0.dist-info/zip-safe
qmkpy-1.2.0.dist-info/RECORD
