Metadata-Version: 2.1
Name: qmkpy
Version: 1.2.0
Summary: Framework for solving the Quadratic Multiple Knapsack Problem (QMKP)
Home-page: https://github.com/klb2/qmkpy
Author: Karl Besser
Author-email: k.besser@tu-bs.de
License: GPLv3
Project-URL: Documentation, https://qmkpy.readthedocs.io
Project-URL: Source Code, https://github.com/klb2/qmkpy
Keywords: quadratic multiple knapsack problem,knapsack problem,operations research
Classifier: Intended Audience :: Science/Research
Classifier: Intended Audience :: Telecommunications Industry
Classifier: License :: OSI Approved :: GNU General Public License v3 (GPLv3)
Classifier: Programming Language :: Python :: 3
Classifier: Programming Language :: Python :: 3 :: Only
Classifier: Topic :: Scientific/Engineering
Requires-Python: >=3.7
License-File: LICENSE
Requires-Dist: numpy
